examples/__init__.py
examples/beets_config.example.yaml
examples/magapy.example.ini
examples/setup_beets.example.py
magapy-0.1.2.dist-info/licenses/LICENSE
tests/__init__.py
tests/test_audio_utils.py
tests/test_utils.py
magapy-0.1.2.dist-info/METADATA
magapy-0.1.2.dist-info/WHEEL
magapy-0.1.2.dist-info/entry_points.txt
magapy-0.1.2.dist-info/top_level.txt
magapy-0.1.2.dist-info/RECORD
