Metadata-Version: 2.4
Name: magapy
Version: 0.1.2
Summary: Music library management tool for organizing and downloading high-quality audio
Home-page: https://github.com/geooooooorges/magapy
Author: Georges Khawam
Author-email: your.email@example.com
Project-URL: Bug Tracker, https://github.com/geooooooorges/magapy/issues
Project-URL: Documentation, https://github.com/geooooooorges/magapy
Project-URL: Source Code, https://github.com/geooooooorges/magapy
Classifier: Development Status :: 3 - Alpha
Classifier: Intended Audience :: End Users/Desktop
Classifier: License :: OSI Approved :: MIT License
Classifier: Programming Language :: Python :: 3
Classifier: Programming Language :: Python :: 3.7
Classifier: Programming Language :: Python :: 3.8
Classifier: Programming Language :: Python :: 3.9
Classifier: Topic :: Multimedia :: Sound/Audio
Requires-Python: >=3.7
License-File: LICENSE
Requires-Dist: tqdm>=4.64.0
Requires-Dist: mutagen>=1.45.1
Requires-Dist: beets>=1.6.0
Requires-Dist: pathlib>=1.0.1
Requires-Dist: pytest>=7.0.0
Requires-Dist: Pillow>=9.0.0
Requires-Dist: requests>=2.28.0
Dynamic: author
Dynamic: author-email
Dynamic: classifier
Dynamic: description
Dynamic: description-content-type
Dynamic: home-page
Dynamic: license-file
Dynamic: project-url
Dynamic: requires-dist
Dynamic: requires-python
Dynamic: summary
